__init__.py
voiceflow/__init__.py
voiceflow/defaults.py
voiceflow/interact.py
voiceflow/user.py
voiceflow/variables.py
voiceflow-1.0.6.dist-info/LICENSE
voiceflow-1.0.6.dist-info/METADATA
voiceflow-1.0.6.dist-info/WHEEL
voiceflow-1.0.6.dist-info/top_level.txt
voiceflow-1.0.6.dist-info/RECORD
