Metadata-Version: 2.1
Name: voiceflow
Version: 1.0.6
Summary: A Python package for Voiceflow API.
Author-email: Daian Gan <daian@ganmedia.com>
License: Copyright (c) 2018 The Python Packaging Authority        
Project-URL: Homepage, https://github.com/daiangan/voiceflow-python
Project-URL: Bug Tracker, https://github.com/daiangan/voiceflow-python/issues
Classifier: Programming Language :: Python :: 3
Classifier: License :: OSI Approved :: MIT License
Classifier: Operating System :: OS Independent
Classifier: Topic :: Communications :: Chat
Requires-Python: >=3.7
License-File: LICENSE
